LICENSE
MANIFEST.in
README.md
pyproject.toml
requirements.txt
setup.cfg
setup.py
yolov7/__init__.py
yolov7/detect.py
yolov7/export.py
yolov7/helpers.py
yolov7/hubconf.py
yolov7/test.py
yolov7/train.py
yolov7/train_aux.py
yolov7/models/__init__.py
yolov7/models/common.py
yolov7/models/experimental.py
yolov7/models/yolo.py
yolov7/utils/__init__.py
yolov7/utils/activations.py
yolov7/utils/add_nms.py
yolov7/utils/autoanchor.py
yolov7/utils/datasets.py
yolov7/utils/general.py
yolov7/utils/google_utils.py
yolov7/utils/loss.py
yolov7/utils/metrics.py
yolov7/utils/plots.py
yolov7/utils/torch_utils.py
yolov7/utils/aws/__init__.py
yolov7/utils/aws/resume.py
yolov7/utils/wandb_logging/__init__.py
yolov7/utils/wandb_logging/log_dataset.py
yolov7/utils/wandb_logging/wandb_utils.py
yolov7detect.egg-info/PKG-INFO
yolov7detect.egg-info/SOURCES.txt
yolov7detect.egg-info/dependency_links.txt
yolov7detect.egg-info/requires.txt
yolov7detect.egg-info/top_level.txt